cubexplain/__init__.py
cubexplain/__main__.py
cubexplain/atotiwatcher.py
cubexplain/commande_line.py
cubexplain/dataprocessor.py
cubexplain/start_session.py
cubexplain-0.1.14.dist-info/entry_points.txt
cubexplain-0.1.14.dist-info/WHEEL
cubexplain-0.1.14.dist-info/METADATA
cubexplain-0.1.14.dist-info/RECORD
